History.rst
LICENSE.txt
MANIFEST.in
README.rst
requirements.txt
setup.cfg
setup.py
qirest_client/__init__.py
qirest_client/choices.py
qirest_client.egg-info/PKG-INFO
qirest_client.egg-info/SOURCES.txt
qirest_client.egg-info/dependency_links.txt
qirest_client.egg-info/requires.txt
qirest_client.egg-info/top_level.txt
qirest_client/helpers/__init__.py
qirest_client/helpers/database.py
qirest_client/model/__init__.py
qirest_client/model/admin.py
qirest_client/model/clinical.py
qirest_client/model/common.py
qirest_client/model/facade.py
qirest_client/model/imaging.py
qirest_client/model/subject.py
qirest_client/model/uom.py
test/__init__.py
test/unit/__init__.py
test/unit/test_choices.py
test/unit/test_model.py